asyncgui_ext/synctools/__init__.py
asyncgui_ext/synctools/all.py
asyncgui_ext/synctools/box.py
asyncgui_ext/synctools/event.py
asyncgui_ext_synctools-0.2.0.dist-info/LICENSE
asyncgui_ext_synctools-0.2.0.dist-info/METADATA
asyncgui_ext_synctools-0.2.0.dist-info/WHEEL
asyncgui_ext_synctools-0.2.0.dist-info/RECORD
